{"id":2758157131,"id_str":"2758157131","name":"Sashko Sashko","screen_name":"barmacuca","location":"","profile_location":null,"description":"","url":null,"entities":{"description":{"urls":[]}},"protected":false,"followers_count":27,"friends_count":863,"listed_count":0,"created_at":"Sat Aug 23 08:07:23 +0000 2014","favourites_count":396,"utc_offset":null,"time_zone":null,"geo_enabled":true,"verified":false,"statuses_count":46,"lang":null,"status":{"created_at":"Mon Sep 07 07:58:33 +0000 2020","id":1302878913056714800,"id_str":"1302878913056714753","text":"@anatoliisharii Воно тобі треба?","truncated":false,"entities":{"hashtags":[],"symbols":[],"user_mentions":[{"screen_name":"anatoliisharii","name":"Анатолий Шарий","id":2420953021,"id_str":"2420953021","indices":[0,15]}],"urls":[]},"source":"<a href=\"https://mobile.twitter.com\" rel=\"nofollow\">Twitter Web App</a>","in_reply_to_status_id":1302871052683546600,"in_reply_to_status_id_str":"1302871052683546624","in_reply_to_user_id":2420953021,"in_reply_to_user_id_str":"2420953021","in_reply_to_screen_name":"anatoliisharii","geo":null,"coordinates":null,"place":null,"contributors":null,"is_quote_status":false,"retweet_count":0,"favorite_count":0,"favorited":false,"retweeted":false,"lang":"uk"},"contributors_enabled":false,"is_translator":false,"is_translation_enabled":false,"profile_background_color":"C0DEED","profile_background_image_url":"http://abs.twimg.com/images/themes/theme1/bg.png","profile_background_image_url_https":"https://abs.twimg.com/images/themes/theme1/bg.png","profile_background_tile":false,"profile_image_url":"http://abs.twimg.com/sticky/default_profile_images/default_profile_normal.png","profile_image_url_https":"https://abs.twimg.com/sticky/default_profile_images/default_profile_normal.png","profile_link_color":"1DA1F2","profile_sidebar_border_color":"C0DEED","profile_sidebar_fill_color":"DDEEF6","profile_text_color":"333333","profile_use_background_image":true,"has_extended_profile":false,"default_profile":true,"default_profile_image":true,"following":false,"follow_request_sent":false,"notifications":false,"translator_type":"none"}