{"id":3416760310,"id_str":"3416760310","name":"Сергей Кучерук","screen_name":"BnTlcg","location":"Ukraine","profile_location":{"id":"084d0d0155787e9d","url":"https://api.twitter.com/1.1/geo/id/084d0d0155787e9d.json","place_type":"unknown","name":"Ukraine","full_name":"Ukraine","country_code":"","country":"","contained_within":[],"bounding_box":null,"attributes":{}},"description":"","url":null,"entities":{"description":{"urls":[]}},"protected":false,"followers_count":0,"friends_count":18,"listed_count":0,"created_at":"Wed Aug 12 01:54:48 +0000 2015","favourites_count":10,"utc_offset":null,"time_zone":null,"geo_enabled":false,"verified":false,"statuses_count":12,"lang":null,"status":{"created_at":"Sat Oct 20 07:28:49 +0000 2018","id":1053548578654863400,"id_str":"1053548578654863360","text":"Очень странная история 1-1: https://t.co/DsoBTEklNd на @YouTube","truncated":false,"entities":{"hashtags":[],"symbols":[],"user_mentions":[{"screen_name":"YouTube","name":"YouTube","id":10228272,"id_str":"10228272","indices":[55,63]}],"urls":[{"url":"https://t.co/DsoBTEklNd","expanded_url":"http://youtu.be/4oK8DW4JP3Y?a","display_url":"youtu.be/4oK8DW4JP3Y?a","indices":[28,51]}]},"source":"<a href=\"https://www.google.com/\" rel=\"nofollow\">Google</a>","in_reply_to_status_id":null,"in_reply_to_status_id_str":null,"in_reply_to_user_id":null,"in_reply_to_user_id_str":null,"in_reply_to_screen_name":null,"geo":null,"coordinates":null,"place":null,"contributors":null,"is_quote_status":false,"retweet_count":0,"favorite_count":0,"favorited":false,"retweeted":false,"possibly_sensitive":false,"lang":"ru"},"contributors_enabled":false,"is_translator":false,"is_translation_enabled":false,"profile_background_color":"000000","profile_background_image_url":"http://abs.twimg.com/images/themes/theme1/bg.png","profile_background_image_url_https":"https://abs.twimg.com/images/themes/theme1/bg.png","profile_background_tile":false,"profile_image_url":"http://pbs.twimg.com/profile_images/787580690154020865/08QB9psK_normal.jpg","profile_image_url_https":"https://pbs.twimg.com/profile_images/787580690154020865/08QB9psK_normal.jpg","profile_banner_url":"https://pbs.twimg.com/profile_banners/3416760310/1476607952","profile_link_color":"E81C4F","profile_sidebar_border_color":"000000","profile_sidebar_fill_color":"000000","profile_text_color":"000000","profile_use_background_image":false,"has_extended_profile":false,"default_profile":false,"default_profile_image":false,"following":false,"follow_request_sent":false,"notifications":false,"translator_type":"none"}